discord_qalib-2.5.14.dist-info/licenses/LICENSE
qalib/__init__.py
qalib/context.py
qalib/interaction.py
qalib/py.typed
qalib/renderer.py
qalib/template_engines/__init__.py
qalib/template_engines/formatter.py
qalib/template_engines/jinja2.py
qalib/template_engines/template_engine.py
qalib/translators/__init__.py
qalib/translators/deserializer.py
qalib/translators/events.py
qalib/translators/factory.py
qalib/translators/menu.py
qalib/translators/message_parsing.py
qalib/translators/modal.py
qalib/translators/templater.py
qalib/translators/view.py
qalib/translators/element/__init__.py
qalib/translators/element/embed.py
qalib/translators/element/expansive.py
qalib/translators/element/types/__init__.py
qalib/translators/element/types/embed.py
qalib/translators/json/__init__.py
qalib/translators/json/components.py
qalib/translators/json/embed.py
qalib/translators/xml/__init__.py
qalib/translators/xml/embed.py
discord_qalib-2.5.14.dist-info/METADATA
discord_qalib-2.5.14.dist-info/WHEEL
discord_qalib-2.5.14.dist-info/top_level.txt
discord_qalib-2.5.14.dist-info/RECORD
