Metadata-Version: 2.4
Name: discord-qalib
Version: 2.5.14
Summary: Discord library built on discord.py to simplify source code by rendering templates of embeds and menus
Home-page: https://github.com/YousefEZ/discord-qalib
Author: Yousef Zaher
Author-email: YousefEZ <syberprojects@gmail.com>
License: MIT
Project-URL: Homepage, https://github.com/YousefEZ/discord-qalib
Project-URL: Bug Tracker, https://github.com/YousefEZ/discord-qalib/issues
Classifier: Programming Language :: Python :: 3
Classifier: License :: OSI Approved :: MIT License
Classifier: Operating System :: OS Independent
Requires-Python: >=3.8.0
License-File: LICENSE
Requires-Dist: discord==2.3.2
Requires-Dist: compose==1.5.0
Requires-Dist: emoji==2.9.0
Requires-Dist: discord-emoji==1.4.2
Requires-Dist: Jinja2>=3.1.2
Requires-Dist: mock==5.1.0
Requires-Dist: typing-extensions==4.9.0
Requires-Dist: deprecated==1.2.14
Requires-Dist: asyncio~=3.4.3
Requires-Dist: setuptools==70.0.0
Dynamic: author
Dynamic: home-page
Dynamic: license
Dynamic: license-file
Dynamic: requires-python
